flake8_jira_ticket_checker/__init__.py
flake8_jira_ticket_checker/__version__.py
flake8_jira_ticket_checker/jira_checker.py
flake8_jira_ticket_checker-0.1.2.dist-info/licenses/LICENSE
flake8_jira_ticket_checker-0.1.2.dist-info/METADATA
flake8_jira_ticket_checker-0.1.2.dist-info/WHEEL
flake8_jira_ticket_checker-0.1.2.dist-info/entry_points.txt
flake8_jira_ticket_checker-0.1.2.dist-info/top_level.txt
flake8_jira_ticket_checker-0.1.2.dist-info/RECORD
