Metadata-Version: 2.4
Name: flake8-jira-ticket-checker
Version: 0.1.2
Summary: Flake8 plugin to check JIRA ticket status
Home-page: https://github.com/lauernik/flake8-jira-ticket-checker
Author: Nikita Lauer
Author-email: Nikita Lauer <lauernik@gmail.com>
License: MIT
Project-URL: Homepage, https://github.com/lauernik/flake8-jira-ticket-checker
Project-URL: Repository, https://github.com/lauernik/flake8-jira-ticket-checker
Project-URL: Issues, https://github.com/lauernik/flake8-jira-ticket-checker/issues
Keywords: flake8,jira,ticket,checker,linter
Classifier: Framework :: Flake8
Classifier: Environment :: Console
Classifier: Intended Audience :: Developers
Classifier: License :: OSI Approved :: MIT License
Classifier: Programming Language :: Python :: 3
Classifier: Programming Language :: Python :: 3.8
Classifier: Programming Language :: Python :: 3.9
Classifier: Programming Language :: Python :: 3.10
Classifier: Programming Language :: Python :: 3.11
Classifier: Programming Language :: Python :: 3.12
Classifier: Topic :: Software Development :: Libraries :: Python Modules
Classifier: Topic :: Software Development :: Quality Assurance
Requires-Python: >=3.8
License-File: LICENSE
Requires-Dist: flake8<7.0.0,>=6.0.0
Requires-Dist: jira<4.0.0,>=3.0.0
Dynamic: author
Dynamic: home-page
Dynamic: license-file
Dynamic: requires-python
